{"cameraMode":{"drawMode":0,"name":"Shaded","section":"Shading Mode"},"sceneLighting":true,"audioPlay":false,"sceneViewState":{"showFog":true,"showMaterialUpdate":false,"showSkybox":true,"showFlares":true,"showImageEffects":true,"showParticleSystems":true},"in2DMode":false,"pivot":{"x":21.937191009521486,"y":8.057259559631348,"z":14.387069702148438},"rotation":{"x":0.035992179065942767,"y":-0.004496959503740072,"z":0.00016318709822371602,"w":0.9993465542793274},"size":40.26345443725586,"orthographic":false}